pyoneer/__init__.py
pyoneer/activations/__init__.py
pyoneer/activations/activations_impl.py
pyoneer/activations/activations_test.py
pyoneer/debugging/__init__.py
pyoneer/debugging/debugging_impl.py
pyoneer/debugging/debugging_test.py
pyoneer/distributions/__init__.py
pyoneer/distributions/distributions_impl.py
pyoneer/distributions/distributions_test.py
pyoneer/initializers/__init__.py
pyoneer/initializers/initializers_impl.py
pyoneer/initializers/initializers_test.py
pyoneer/layers/__init__.py
pyoneer/layers/layers_impl.py
pyoneer/layers/layers_test.py
pyoneer/manip/__init__.py
pyoneer/manip/array_ops.py
pyoneer/manip/array_ops_test.py
pyoneer/manip/indexing_ops.py
pyoneer/manip/indexing_ops_test.py
pyoneer/math/__init__.py
pyoneer/math/angle_ops.py
pyoneer/math/angle_ops_test.py
pyoneer/math/logical_ops.py
pyoneer/math/logical_ops_test.py
pyoneer/math/math_ops.py
pyoneer/math/math_ops_test.py
pyoneer/metrics/__init__.py
pyoneer/metrics/metrics_impl.py
pyoneer/metrics/metrics_test.py
pyoneer/moments/__init__.py
pyoneer/moments/moments_impl.py
pyoneer/moments/moments_test.py
pyoneer/nn/__init__.py
pyoneer/nn/nn_impl.py
pyoneer/nn/nn_impl_test.py
pyoneer/rl/__init__.py
pyoneer/rl/losses/__init__.py
pyoneer/rl/losses/policy_gradient_ops.py
pyoneer/rl/losses/policy_gradient_ops_test.py
pyoneer/rl/strategies/__init__.py
pyoneer/rl/strategies/strategies_impl.py
pyoneer/rl/strategies/strategies_test.py
pyoneer/rl/targets/__init__.py
pyoneer/rl/targets/target_ops.py
pyoneer/rl/targets/target_ops_test.py
pyoneer/rl/wrappers/__init__.py
pyoneer/rl/wrappers/batch_impl.py
pyoneer/rl/wrappers/batch_process_impl.py
pyoneer/rl/wrappers/batch_process_test.py
pyoneer/rl/wrappers/batch_test.py
pyoneer/rl/wrappers/observation_impl.py
pyoneer/rl/wrappers/observation_test.py
pyoneer/rl/wrappers/process_impl.py
pyoneer/rl/wrappers/process_test.py
pyoneer/schedules/__init__.py
pyoneer/schedules/cyclic_schedule_impl.py
pyoneer/schedules/cyclic_schedule_test.py
fomoro_pyoneer-0.2.0.dist-info/LICENSE
fomoro_pyoneer-0.2.0.dist-info/METADATA
fomoro_pyoneer-0.2.0.dist-info/WHEEL
fomoro_pyoneer-0.2.0.dist-info/top_level.txt
fomoro_pyoneer-0.2.0.dist-info/RECORD
