Metadata-Version: 2.1
Name: fomoro-pyoneer
Version: 0.2.0
Summary: Tensor utilities, reinforcement learning, and more!
Home-page: https://github.com/fomorians/pyoneer
Author: Fomoro AI
Author-email: team@fomoro.com
License: Apache 2.0
Download-URL: https://github.com/fomorians/pyoneer/archive/v0.2.tar.gz
Keywords: tensorflow,machine learning,reinforcement learning,eager execution,deep learning
Platform: UNKNOWN
Classifier: Intended Audience :: Science/Research
Classifier: Intended Audience :: Developers
Classifier: License :: OSI Approved :: Apache Software License
Classifier: Programming Language :: Python :: 2
Classifier: Programming Language :: Python :: 2.7
Classifier: Programming Language :: Python :: 3
Classifier: Programming Language :: Python :: 3.5
Classifier: Programming Language :: Python :: 3.6
Classifier: Operating System :: OS Independent
Classifier: Development Status :: 3 - Alpha
Requires-Dist: gym
Provides-Extra: dev
Requires-Dist: pre-commit ; extra == 'dev'
